trusspy/__init__.py
trusspy/model.py
trusspy/core/__init__.py
trusspy/core/analysis.py
trusspy/core/boundary.py
trusspy/core/element.py
trusspy/core/external_force.py
trusspy/core/node.py
trusspy/core/result.py
trusspy/elements/__init__.py
trusspy/elements/element_definition.py
trusspy/handlers/__init__.py
trusspy/handlers/handler_boundary.py
trusspy/handlers/handler_element.py
trusspy/handlers/handler_extforce.py
trusspy/handlers/handler_node.py
trusspy/handlers/handler_result.py
trusspy/handlers/handler_settings.py
trusspy/materials/__init__.py
trusspy/materials/material_definition.py
trusspy/misc/__init__.py
trusspy/misc/license_info.py
trusspy/solvers/__init__.py
trusspy/solvers/tpsolver.py
trusspy/solvers/zerosearch.py
trusspy/tools/__init__.py
trusspy/tools/helper_functions2.py
trusspy/tools/movie_generator.py
trusspy/tools/plot_utilities.py
trusspy-20221217.dist-info/LICENSE
trusspy-20221217.dist-info/METADATA
trusspy-20221217.dist-info/WHEEL
trusspy-20221217.dist-info/top_level.txt
trusspy-20221217.dist-info/RECORD
