Metadata-Version: 2.1
Name: trusspy
Version: 20221217
Summary: Truss Solver for Python
Home-page: https://github.com/adtzlr/trusspy
Author: Andreas Dutzler
Author-email: a.dutzler@gmail.com
License: GNU GPLv3
License-File: LICENSE
